gqlite.py
gqlite-0.4.0.dist-info/LICENSE
gqlite-0.4.0.dist-info/METADATA
gqlite-0.4.0.dist-info/WHEEL
gqlite-0.4.0.dist-info/RECORD
